{"trailingStockBasedCompensation":[{"value":30126000,"timestamp":1569801600}],"annualCurrentLiabilities":[{"value":56636000,"timestamp":1483142400},{"value":158544000,"timestamp":1514678400},{"value":126121000,"timestamp":1538265600}],"trailingChangeInInventory":[{"value":-4673000,"timestamp":1569801600}],"annualDepreciationAndAmortization":[{"value":10529000,"timestamp":1483142400},{"value":21984000,"timestamp":1514678400}],"quarterlyInventory":[{"value":5789000,"timestamp":1483142400},{"value":7279000,"timestamp":1514678400},{"value":10869000,"timestamp":1538265600}],"annualChangeInInventory":[{"value":-574000,"timestamp":1483142400},{"value":-1253000,"timestamp":1514678400}],"quarterlyOtherIncomeExpense":[{"value":-21000,"timestamp":1483142400},{"value":6050000,"timestamp":1514678400}],"quarterlyCapitalExpenditure":[{"value":-6716000,"timestamp":1483142400},{"value":-21152000,"timestamp":1514678400},{"value":-21285000,"timestamp":1538265600}],"trailingDepreciationAndAmortization":[{"value":32312000,"timestamp":1569801600}],"trailingCashFlowFromContinuingFinancingActivities":[{"value":336291000,"timestamp":1569801600}],"quarterlyCommonStockIssuance":[{"value":52923000,"timestamp":1483142400},{"value":79998000,"timestamp":1514678400},{"value":247696000,"timestamp":1538265600}],"annualOtherNonCashItems":[{"value":-1403000,"timestamp":1483142400},{"value":-226000,"timestamp":1514678400}],"annualInventory":[{"value":3266000,"timestamp":1483142400},{"value":3876000,"timestamp":1514678400},{"value":5789000,"timestamp":1538265600}],"quarterlyInterestExpense":[{"value":429000,"timestamp":1483142400},{"value":424000,"timestamp":1514678400},{"value":433000,"timestamp":1538265600}],"quarterlyCashFlowFromContinuingFinancingActivities":[{"value":54873000,"timestamp":1483142400},{"value":82568000,"timestamp":1514678400},{"value":248804000,"timestamp":1538265600}],"quarterlyInvestmentsAndAdvances":[{"value":18000,"timestamp":1483142400},{"value":1000,"timestamp":1514678400},{"value":0,"timestamp":1538265600}],"trailingOtherNonCashItems":[{"value":381000,"timestamp":1569801600}],"trailingOperatingCashFlow":[{"value":-137678000,"timestamp":1569801600}],"annualCapitalStock":[{"value":0,"timestamp":1483142400},{"value":0,"timestamp":1514678400},{"value":0,"timestamp":1538265600}],"annualStockBasedCompensation":[{"value":5909000,"timestamp":1483142400},{"value":7641000,"timestamp":1514678400}],"annualNetPPE":[{"value":60506000,"timestamp":1483142400},{"value":101521000,"timestamp":1514678400},{"value":115966000,"timestamp":1538265600}],"quarterlyOperatingCashFlow":[{"value":14265000,"timestamp":1483142400},{"value":-2768000,"timestamp":1514678400},{"value":-49221000,"timestamp":1538265600}],"annualOtherIntangibleAssets":[{"value":10650000,"timestamp":1483142400},{"value":83003000,"timestamp":1514678400},{"value":87508000,"timestamp":1538265600}],"quarterlyChangeInCashSupplementalAsReported":[{"value":62522000,"timestamp":1483142400},{"value":58788000,"timestamp":1514678400},{"value":178303000,"timestamp":1538265600}],"annualGrossProfit":[{"value":52280000,"timestamp":1483142400},{"value":113885000,"timestamp":1514678400}],"annualOperatingCashFlow":[{"value":-52562000,"timestamp":1483142400},{"value":-58180000,"timestamp":1514678400}],"quarterlyAccumulatedDepreciation":[{"value":-36652000,"timestamp":1483142400}],"quarterlyOtherNonCurrentAssets":[{"value":-1000,"timestamp":1483142400}],"quarterlyBasicEPS":[{"value":-0.103561,"timestamp":1483142400},{"value":-0.131189,"timestamp":1514678400}],"trailingPretaxIncome":[{"value":-122377000,"timestamp":1569801600}],"quarterlyOtherCurrentLiabilities":[{"value":12130000,"timestamp":1483142400},{"value":29013000,"timestamp":1514678400},{"value":22577000,"timestamp":1538265600}],"quarterlyTaxProvision":[{"value":573000,"timestamp":1483142400},{"value":17000,"timestamp":1514678400},{"value":8000,"timestamp":1538265600}],"quarterlyResearchAndDevelopment":[{"value":32791000,"timestamp":1483142400},{"value":51796000,"timestamp":1514678400},{"value":50396000,"timestamp":1538265600}],"quarterlyBasicAverageShares":[{"value":226262336,"timestamp":1483142400},{"value":229462336,"timestamp":1514678400}],"trailingNetIncome":[{"value":-122185000,"timestamp":1569801600}],"annualCashCashEquivalentsAndMarketableSecurities":[{"value":305208000,"timestamp":1483142400},{"value":172352000,"timestamp":1514678400},{"value":411831000,"timestamp":1538265600}],"quarterlyNetPPE":[{"value":115966000,"timestamp":1483142400},{"value":123054000,"timestamp":1514678400},{"value":142631000,"timestamp":1538265600}],"quarterlyPretaxIncome":[{"value":-22906000,"timestamp":1483142400},{"value":-1456000,"timestamp":1514678400},{"value":-30095000,"timestamp":1538265600}],"quarterlyPurchaseOfBusiness":[{"value":0,"timestamp":1483142400},{"value":-6000,"timestamp":1514678400}],"trailingChangeInCashSupplementalAsReported":[{"value":110555000,"timestamp":1569801600}],"annualOtherCurrentLiabilities":[{"value":13913000,"timestamp":1483142400},{"value":9265000,"timestamp":1514678400},{"value":12130000,"timestamp":1538265600}],"annualNetOtherInvestingChanges":[{"value":1000,"timestamp":1483142400}],"quarterlyOtherShortTermInvestments":[{"value":336000,"timestamp":1483142400},{"value":190646000,"timestamp":1514678400},{"value":356000,"timestamp":1538265600}],"quarterlyFreeCashFlow":[{"value":7549000,"timestamp":1483142400},{"value":-23920000,"timestamp":1514678400},{"value":-70506000,"timestamp":1538265600}],"annualChangeInCashSupplementalAsReported":[{"value":-106753000,"timestamp":1483142400},{"value":239848000,"timestamp":1514678400}],"annualRepaymentOfDebt":[{"value":-1643000,"timestamp":1483142400},{"value":-2148000,"timestamp":1514678400}],"annualChangeInWorkingCapital":[{"value":-7962000,"timestamp":1483142400},{"value":-40961000,"timestamp":1514678400}],"annualGrossPPE":[{"value":82814000,"timestamp":1483142400},{"value":129224000,"timestamp":1514678400},{"value":152618000,"timestamp":1538265600}],"annualDilutedEPS":[{"value":-0.378556,"timestamp":1483142400},{"value":-0.212,"timestamp":1514678400}],"trailingChangeInWorkingCapital":[{"value":-78583000,"timestamp":1569801600}],"annualPretaxIncome":[{"value":-85905000,"timestamp":1483142400},{"value":-47662000,"timestamp":1514678400}],"quarterlyDepreciationAndAmortization":[{"value":4985000,"timestamp":1483142400},{"value":8225000,"timestamp":1514678400},{"value":8492000,"timestamp":1538265600}],"annualBasicEPS":[{"value":-0.378556,"timestamp":1483142400},{"value":-0.212,"timestamp":1514678400}],"annualGoodwill":[{"value":534000,"timestamp":1483142400},{"value":534000,"timestamp":1514678400},{"value":534000,"timestamp":1538265600}],"annualOtherNonCurrentLiabilities":[{"value":1382000,"timestamp":1483142400}],"quarterlyDilutedAverageShares":[{"value":226262336,"timestamp":1483142400},{"value":229462336,"timestamp":1514678400}],"quarterlyTotalNonCurrentAssets":[{"value":204025000,"timestamp":1483142400},{"value":218047000,"timestamp":1514678400},{"value":237113000,"timestamp":1538265600}],"quarterlyTotalAssets":[{"value":652986000,"timestamp":1483142400},{"value":722369000,"timestamp":1514678400},{"value":738408000,"timestamp":1538265600}],"annualInterestExpense":[{"value":676000,"timestamp":1483142400},{"value":1721000,"timestamp":1514678400}],"quarterlyOtherIntangibleAssets":[{"value":87508000,"timestamp":1483142400}],"annualCapitalExpenditure":[{"value":-57742000,"timestamp":1483142400},{"value":-67854000,"timestamp":1514678400}],"trailingGrossProfit":[{"value":126980000,"timestamp":1569801600}],"annualOperatingIncome":[{"value":-60996000,"timestamp":1483142400},{"value":-53853000,"timestamp":1514678400}],"annualOtherIncomeExpense":[{"value":-26314000,"timestamp":1483142400},{"value":5966000,"timestamp":1514678400}],"annualInvestingCashFlow":[{"value":-52549000,"timestamp":1483142400},{"value":-67148000,"timestamp":1514678400}],"quarterlyGainsLossesNotAffectingRetainedEarnings":[{"value":318628000,"timestamp":1483142400},{"value":508242000,"timestamp":1514678400},{"value":566747000,"timestamp":1538265600}],"annualTotalRevenue":[{"value":61598000,"timestamp":1483142400},{"value":127575000,"timestamp":1514678400}],"quarterlyCashCashEquivalentsAndMarketableSecurities":[{"value":411831000,"timestamp":1483142400},{"value":475536000,"timestamp":1514678400},{"value":463664000,"timestamp":1538265600}],"quarterlyCashAndCashEquivalents":[{"value":411495000,"timestamp":1483142400},{"value":284890000,"timestamp":1514678400},{"value":463308000,"timestamp":1538265600}],"trailingCapitalExpenditure":[{"value":-82710000,"timestamp":1569801600}],"trailingInvestingCashFlow":[{"value":-88057000,"timestamp":1569801600}],"annualAccountsPayable":[{"value":6218000,"timestamp":1483142400},{"value":52538000,"timestamp":1514678400},{"value":41721000,"timestamp":1538265600}],"quarterlyBeginningCashPosition":[{"value":293310000,"timestamp":1483142400},{"value":353176000,"timestamp":1514678400},{"value":284890000,"timestamp":1538265600}],"quarterlyAccountsPayable":[{"value":41721000,"timestamp":1483142400},{"value":16881000,"timestamp":1514678400},{"value":21813000,"timestamp":1538265600}],"trailingInterestExpense":[{"value":1707000,"timestamp":1569801600}],"quarterlyCapitalStock":[{"value":0,"timestamp":1483142400},{"value":0,"timestamp":1514678400},{"value":0,"timestamp":1538265600}],"annualCashFlowFromContinuingFinancingActivities":[{"value":-1643000,"timestamp":1483142400},{"value":365177000,"timestamp":1514678400}],"trailingRepaymentOfDebt":[{"value":-2745000,"timestamp":1569801600}],"trailingTotalRevenue":[{"value":144380000,"timestamp":1569801600}],"annualNonCurrentDeferredRevenue":[{"value":273414000,"timestamp":1483142400},{"value":214026000,"timestamp":1514678400},{"value":205647000,"timestamp":1538265600}],"annualEndCashPosition":[{"value":172106000,"timestamp":1483142400},{"value":411495000,"timestamp":1514678400}],"quarterlyStockBasedCompensation":[{"value":0,"timestamp":1483142400},{"value":7641000,"timestamp":1514678400},{"value":4499000,"timestamp":1538265600}],"quarterlyEbitda":[{"value":-17492000,"timestamp":1483142400},{"value":7193000,"timestamp":1514678400},{"value":-21170000,"timestamp":1538265600}],"quarterlyTotalRevenue":[{"value":20397000,"timestamp":1483142400},{"value":63779000,"timestamp":1514678400},{"value":28662000,"timestamp":1538265600}],"trailingTaxProvision":[{"value":45000,"timestamp":1569801600}],"annualNetIncomeContinuousOperations":[{"value":-85950000,"timestamp":1483142400},{"value":-48262000,"timestamp":1514678400}],"annualDilutedAverageShares":[{"value":226262336,"timestamp":1483142400},{"value":226262336,"timestamp":1514678400}],"annualCashAndCashEquivalents":[{"value":303680000,"timestamp":1483142400},{"value":172106000,"timestamp":1514678400},{"value":411495000,"timestamp":1538265600}],"quarterlyTotalLiabilitiesNetMinorityInterest":[{"value":385986000,"timestamp":1483142400},{"value":337879000,"timestamp":1514678400},{"value":322003000,"timestamp":1538265600}],"annualCurrentDeferredRevenue":[{"value":33466000,"timestamp":1483142400},{"value":77346000,"timestamp":1514678400},{"value":66027000,"timestamp":1538265600}],"trailingResearchAndDevelopment":[{"value":212835000,"timestamp":1569801600}],"quarterlyInvestingCashFlow":[{"value":-6616000,"timestamp":1483142400},{"value":-21011000,"timestamp":1514678400},{"value":-21280000,"timestamp":1538265600}],"trailingEndCashPosition":[{"value":463731000,"timestamp":1569801600}],"quarterlyGrossProfit":[{"value":17619000,"timestamp":1483142400},{"value":59304000,"timestamp":1514678400},{"value":24432000,"timestamp":1538265600}],"annualInvestmentsAndAdvances":[{"value":66000,"timestamp":1483142400},{"value":19000,"timestamp":1514678400},{"value":18000,"timestamp":1538265600}],"quarterlyEndCashPosition":[{"value":353176000,"timestamp":1483142400},{"value":411495000,"timestamp":1514678400},{"value":463308000,"timestamp":1538265600}],"quarterlyNetIncomeCommonStockholders":[{"value":-23432000,"timestamp":1483142400},{"value":-1352000,"timestamp":1514678400},{"value":-30103000,"timestamp":1538265600}],"trailingOperatingIncome":[{"value":-130971000,"timestamp":1569801600}],"trailingSellingGeneralAndAdministration":[{"value":45273000,"timestamp":1569801600}],"quarterlyCurrentLiabilities":[{"value":126121000,"timestamp":1483142400},{"value":135993000,"timestamp":1514678400},{"value":128123000,"timestamp":1538265600}],"quarterlyGrossPPE":[{"value":152618000,"timestamp":1483142400}],"annualGainsLossesNotAffectingRetainedEarnings":[{"value":139301000,"timestamp":1483142400},{"value":-18307000,"timestamp":1514678400},{"value":318628000,"timestamp":1538265600}],"trailingFreeCashFlow":[{"value":-220388000,"timestamp":1569801600}],"annualCostOfRevenue":[{"value":9318000,"timestamp":1483142400},{"value":13690000,"timestamp":1514678400}],"trailingOperatingExpense":[{"value":257951000,"timestamp":1569801600}],"annualAccumulatedDepreciation":[{"value":-22308000,"timestamp":1483142400},{"value":-27703000,"timestamp":1514678400},{"value":-36652000,"timestamp":1538265600}],"annualOperatingExpense":[{"value":113276000,"timestamp":1483142400},{"value":167738000,"timestamp":1514678400}],"annualOtherNonCurrentAssets":[{"value":78000,"timestamp":1483142400},{"value":-1000,"timestamp":1514678400},{"value":-1000,"timestamp":1538265600}],"annualTotalNonCurrentLiabilitiesNetMinorityInterest":[{"value":301465000,"timestamp":1483142400},{"value":264375000,"timestamp":1514678400},{"value":259865000,"timestamp":1538265600}],"annualResearchAndDevelopment":[{"value":85496000,"timestamp":1483142400},{"value":143040000,"timestamp":1514678400}],"quarterlyOtherNonCashItems":[{"value":78000,"timestamp":1483142400},{"value":-33000,"timestamp":1514678400},{"value":182000,"timestamp":1538265600}],"trailingBeginningCashPosition":[{"value":353176000,"timestamp":1569801600}],"quarterlyNonCurrentDeferredRevenue":[{"value":205647000,"timestamp":1483142400},{"value":140553000,"timestamp":1514678400},{"value":126067000,"timestamp":1538265600}],"trailingNetIncomeContinuousOperations":[{"value":-122422000,"timestamp":1569801600}],"annualTotalLiabilitiesNetMinorityInterest":[{"value":358101000,"timestamp":1483142400},{"value":422919000,"timestamp":1514678400},{"value":385986000,"timestamp":1538265600}],"quarterlyOperatingIncome":[{"value":-21629000,"timestamp":1483142400},{"value":-2396000,"timestamp":1514678400},{"value":-36874000,"timestamp":1538265600}],"annualCurrentAssets":[{"value":318125000,"timestamp":1483142400},{"value":189637000,"timestamp":1514678400},{"value":448961000,"timestamp":1538265600}],"quarterlyRetainedEarnings":[{"value":-245771000,"timestamp":1483142400},{"value":-336501000,"timestamp":1514678400},{"value":-366604000,"timestamp":1538265600}],"quarterlyCurrentAssets":[{"value":448961000,"timestamp":1483142400},{"value":504322000,"timestamp":1514678400},{"value":501295000,"timestamp":1538265600}],"trailingCostOfRevenue":[{"value":17400000,"timestamp":1569801600}],"quarterlyChangeInWorkingCapital":[{"value":29787000,"timestamp":1483142400},{"value":-18210000,"timestamp":1514678400},{"value":-31797000,"timestamp":1538265600}],"quarterlyCostOfRevenue":[{"value":2778000,"timestamp":1483142400},{"value":4475000,"timestamp":1514678400},{"value":4230000,"timestamp":1538265600}],"annualNetIncomeCommonStockholders":[{"value":-85653000,"timestamp":1483142400},{"value":-48019000,"timestamp":1514678400}],"quarterlyAccountsReceivable":[{"value":18938000,"timestamp":1483142400},{"value":8858000,"timestamp":1514678400},{"value":8931000,"timestamp":1538265600}],"annualBasicAverageShares":[{"value":226262336,"timestamp":1483142400},{"value":226262336,"timestamp":1514678400}],"quarterlyGoodwill":[{"value":534000,"timestamp":1483142400}],"annualRetainedEarnings":[{"value":-112100000,"timestamp":1483142400},{"value":-197753000,"timestamp":1514678400},{"value":-245771000,"timestamp":1538265600}],"quarterlyStockholdersEquity":[{"value":266153000,"timestamp":1483142400},{"value":384490000,"timestamp":1514678400},{"value":416405000,"timestamp":1538265600}],"annualEbitda":[{"value":-74700000,"timestamp":1483142400},{"value":-23957000,"timestamp":1514678400}],"trailingNetIncomeCommonStockholders":[{"value":-122185000,"timestamp":1569801600}],"quarterlyChangeInInventory":[{"value":-623000,"timestamp":1483142400},{"value":272000,"timestamp":1514678400},{"value":-3590000,"timestamp":1538265600}],"annualNetIncome":[{"value":-85653000,"timestamp":1483142400},{"value":-48019000,"timestamp":1514678400}],"annualBeginningCashPosition":[{"value":303680000,"timestamp":1483142400},{"value":172106000,"timestamp":1514678400}],"annualAccountsReceivable":[{"value":3161000,"timestamp":1483142400},{"value":4575000,"timestamp":1514678400},{"value":18938000,"timestamp":1538265600}],"annualCommonStockIssuance":[{"value":0,"timestamp":1483142400},{"value":361725000,"timestamp":1514678400}],"annualOtherShortTermInvestments":[{"value":1528000,"timestamp":1483142400},{"value":246000,"timestamp":1514678400},{"value":336000,"timestamp":1538265600}],"annualFreeCashFlow":[{"value":-110304000,"timestamp":1483142400},{"value":-126034000,"timestamp":1514678400}],"quarterlyNetIncomeContinuousOperations":[{"value":-23479000,"timestamp":1483142400},{"value":-1473000,"timestamp":1514678400},{"value":-30103000,"timestamp":1538265600}],"quarterlyNetIncome":[{"value":-23432000,"timestamp":1483142400},{"value":-1352000,"timestamp":1514678400},{"value":-30103000,"timestamp":1538265600}],"quarterlyOperatingExpense":[{"value":39248000,"timestamp":1483142400},{"value":61700000,"timestamp":1514678400},{"value":61306000,"timestamp":1538265600}],"trailingCommonStockIssuance":[{"value":327869000,"timestamp":1569801600}],"annualOtherCurrentAssets":[{"value":1675000,"timestamp":1483142400},{"value":1628000,"timestamp":1514678400},{"value":398000,"timestamp":1538265600}],"annualSellingGeneralAndAdministration":[{"value":29492000,"timestamp":1483142400},{"value":27090000,"timestamp":1514678400}],"quarterlyCurrentDeferredRevenue":[{"value":66027000,"timestamp":1483142400},{"value":89232000,"timestamp":1514678400},{"value":82585000,"timestamp":1538265600}],"quarterlySellingGeneralAndAdministration":[{"value":7327000,"timestamp":1483142400},{"value":8884000,"timestamp":1514678400},{"value":11252000,"timestamp":1538265600}],"quarterlyDilutedEPS":[{"value":-0.103561,"timestamp":1483142400},{"value":-0.131189,"timestamp":1514678400}],"annualTotalNonCurrentAssets":[{"value":71834000,"timestamp":1483142400},{"value":185076000,"timestamp":1514678400},{"value":204025000,"timestamp":1538265600}],"quarterlyTotalNonCurrentLiabilitiesNetMinorityInterest":[{"value":259865000,"timestamp":1483142400},{"value":201886000,"timestamp":1514678400},{"value":193880000,"timestamp":1538265600}],"annualTaxProvision":[{"value":45000,"timestamp":1483142400},{"value":600000,"timestamp":1514678400}],"quarterlyOtherCurrentAssets":[{"value":398000,"timestamp":1483142400},{"value":7477000,"timestamp":1514678400},{"value":9345000,"timestamp":1538265600}],"annualTotalAssets":[{"value":389959000,"timestamp":1483142400},{"value":374713000,"timestamp":1514678400},{"value":652986000,"timestamp":1538265600}],"annualStockholdersEquity":[{"value":30471000,"timestamp":1483142400},{"value":-49296000,"timestamp":1514678400},{"value":266153000,"timestamp":1538265600}],"quarterlyRepaymentOfDebt":[{"value":-550000,"timestamp":1483142400},{"value":-530000,"timestamp":1514678400},{"value":-924000,"timestamp":1538265600}]}