{"annualDilutedEPS":[{"value":0.000011,"currencyCode":"USD","timestamp":1419984000},{"value":0.000008,"currencyCode":"USD","timestamp":1451520000},{"value":0,"currencyCode":"USD","timestamp":1475193600},{"value":0.130249,"currencyCode":"USD","timestamp":1483142400},{"value":1.43,"currencyCode":"USD","timestamp":1506729600}],"annualSaleOfInvestment":[{"value":0,"currencyCode":"USD","timestamp":1419984000},{"value":421434000,"currencyCode":"USD","timestamp":1451520000}],"annualNonCurrentDeferredTaxesLiabilities":[{"value":5154000,"currencyCode":"USD","timestamp":1419984000},{"value":5043000,"currencyCode":"USD","timestamp":1451520000},{"value":3718000,"currencyCode":"USD","timestamp":1475193600},{"value":3340000,"currencyCode":"USD","timestamp":1483142400}],"quarterlyNetOtherFinancingCharges":[{"value":-162000,"currencyCode":"USD","timestamp":1419984000},{"value":42086000,"currencyCode":"USD","timestamp":1451520000},{"value":-1671000,"currencyCode":"USD","timestamp":1475193600},{"value":-64448000,"currencyCode":"USD","timestamp":1483142400},{"value":-99113000,"currencyCode":"USD","timestamp":1506729600},{"value":154315000,"currencyCode":"USD","timestamp":1514678400},{"value":-2031000,"currencyCode":"USD","timestamp":1522454400},{"value":-7382000,"currencyCode":"USD","timestamp":1530316800},{"value":-4367000,"currencyCode":"USD","timestamp":1538265600}],"quarterlyOtherNonCurrentAssets":[{"value":0,"currencyCode":"USD","timestamp":1419984000},{"value":0,"currencyCode":"USD","timestamp":1451520000},{"value":14920000,"currencyCode":"USD","timestamp":1475193600},{"value":18467000,"currencyCode":"USD","timestamp":1483142400},{"value":43220000,"currencyCode":"USD","timestamp":1506729600},{"value":44037000,"currencyCode":"USD","timestamp":1514678400},{"value":1733000,"currencyCode":"USD","timestamp":1522454400},{"value":4227000,"currencyCode":"USD","timestamp":1530316800},{"value":6581000,"currencyCode":"USD","timestamp":1538265600}],"annualStockholdersEquity":[{"value":85375000,"currencyCode":"USD","timestamp":1419984000},{"value":84143000,"currencyCode":"USD","timestamp":1451520000},{"value":4691489000,"currencyCode":"USD","timestamp":1475193600},{"value":6817449000,"currencyCode":"USD","timestamp":1483142400}],"trailingOtherNonCashItems":[{"value":11099000,"currencyCode":"USD","timestamp":1569801600}],"annualOtherNonCashItems":[{"value":3000,"currencyCode":"USD","timestamp":1419984000},{"value":31000,"currencyCode":"USD","timestamp":1451520000},{"value":-10000,"currencyCode":"USD","timestamp":1475193600},{"value":-39428000,"currencyCode":"USD","timestamp":1483142400}],"quarterlyInvestmentsAndAdvances":[{"value":8281557000,"currencyCode":"USD","timestamp":1419984000},{"value":8294753000,"currencyCode":"USD","timestamp":1451520000},{"value":8815557000,"currencyCode":"USD","timestamp":1475193600},{"value":8916047000,"currencyCode":"USD","timestamp":1483142400},{"value":9186144000,"currencyCode":"USD","timestamp":1506729600}],"quarterlyOperatingCashFlow":[{"value":335000,"currencyCode":"USD","timestamp":1419984000},{"value":129440000,"currencyCode":"USD","timestamp":1451520000},{"value":909000,"currencyCode":"USD","timestamp":1475193600},{"value":245754000,"currencyCode":"USD","timestamp":1483142400},{"value":81854000,"currencyCode":"USD","timestamp":1506729600},{"value":175565000,"currencyCode":"USD","timestamp":1514678400},{"value":115642000,"currencyCode":"USD","timestamp":1522454400},{"value":147300000,"currencyCode":"USD","timestamp":1530316800},{"value":174257000,"currencyCode":"USD","timestamp":1538265600}],"annualBasicAverageShares":[{"value":360778938,"currencyCode":"USD","timestamp":1419984000},{"value":360778938,"currencyCode":"USD","timestamp":1451520000},{"value":360778938,"currencyCode":"USD","timestamp":1475193600},{"value":327541414,"currencyCode":"USD","timestamp":1483142400},{"value":367226395,"currencyCode":"USD","timestamp":1506729600}],"quarterlyNetIncomeContinuousOperations":[{"value":0,"currencyCode":"USD","timestamp":1419984000},{"value":0,"currencyCode":"USD","timestamp":1451520000},{"value":0,"currencyCode":"USD","timestamp":1475193600},{"value":44537000,"currencyCode":"USD","timestamp":1483142400},{"value":114103000,"currencyCode":"USD","timestamp":1506729600},{"value":141359000,"currencyCode":"USD","timestamp":1514678400},{"value":132024000,"currencyCode":"USD","timestamp":1522454400},{"value":144630000,"currencyCode":"USD","timestamp":1530316800},{"value":152926000,"currencyCode":"USD","timestamp":1538265600},{"value":154127000,"currencyCode":"USD","timestamp":1546214400},{"value":146515000,"currencyCode":"USD","timestamp":1553990400}],"quarterlyCashFlowFromContinuingFinancingActivities":[{"value":-175000,"currencyCode":"USD","timestamp":1419984000},{"value":1148446000,"currencyCode":"USD","timestamp":1451520000},{"value":-1685000,"currencyCode":"USD","timestamp":1475193600},{"value":552627000,"currencyCode":"USD","timestamp":1483142400},{"value":-99113000,"currencyCode":"USD","timestamp":1506729600},{"value":586007000,"currencyCode":"USD","timestamp":1514678400},{"value":9713000,"currencyCode":"USD","timestamp":1522454400},{"value":911464000,"currencyCode":"USD","timestamp":1530316800},{"value":-137456000,"currencyCode":"USD","timestamp":1538265600}],"quarterlyCapitalExpenditure":[{"value":-76000,"currencyCode":"USD","timestamp":1419984000},{"value":-51000,"currencyCode":"USD","timestamp":1451520000},{"value":-66000,"currencyCode":"USD","timestamp":1475193600},{"value":-491000,"currencyCode":"USD","timestamp":1483142400},{"value":-187000,"currencyCode":"USD","timestamp":1506729600},{"value":-6935000,"currencyCode":"USD","timestamp":1514678400},{"value":-1676000,"currencyCode":"USD","timestamp":1522454400},{"value":-910000,"currencyCode":"USD","timestamp":1530316800},{"value":-1847000,"currencyCode":"USD","timestamp":1538265600}],"annualChangeInInventory":[{"value":-54000,"currencyCode":"USD","timestamp":1419984000},{"value":-5000,"currencyCode":"USD","timestamp":1451520000},{"value":71000,"currencyCode":"USD","timestamp":1475193600}],"trailingSaleOfInvestment":[{"value":939139000,"currencyCode":"USD","timestamp":1569801600}],"quarterlyNetIncome":[{"value":0,"currencyCode":"USD","timestamp":1419984000},{"value":0,"currencyCode":"USD","timestamp":1451520000},{"value":0,"currencyCode":"USD","timestamp":1475193600},{"value":42662000,"currencyCode":"USD","timestamp":1483142400},{"value":112122000,"currencyCode":"USD","timestamp":1506729600},{"value":139044000,"currencyCode":"USD","timestamp":1514678400},{"value":129912000,"currencyCode":"USD","timestamp":1522454400},{"value":142541000,"currencyCode":"USD","timestamp":1530316800},{"value":150849000,"currencyCode":"USD","timestamp":1538265600},{"value":152049000,"currencyCode":"USD","timestamp":1546214400},{"value":144435000,"currencyCode":"USD","timestamp":1553990400}],"annualInvestingCashFlow":[{"value":-11000,"currencyCode":"USD","timestamp":1419984000},{"value":-732000,"currencyCode":"USD","timestamp":1451520000},{"value":-869000,"currencyCode":"USD","timestamp":1475193600},{"value":-1138169000,"currencyCode":"USD","timestamp":1483142400},{"value":-1140877000,"currencyCode":"USD","timestamp":1506729600}],"trailingStockBasedCompensation":[{"value":4681000,"currencyCode":"USD","timestamp":1569801600}],"annualDepreciationAndAmortization":[{"value":2904000,"currencyCode":"USD","timestamp":1419984000},{"value":2882000,"currencyCode":"USD","timestamp":1451520000},{"value":3030000,"currencyCode":"USD","timestamp":1475193600},{"value":3153000,"currencyCode":"USD","timestamp":1483142400},{"value":3686000,"currencyCode":"USD","timestamp":1506729600}],"trailingCashDividendsPaid":[{"value":-473245000,"currencyCode":"USD","timestamp":1569801600}],"annualInventory":[{"value":442000,"currencyCode":"USD","timestamp":1419984000},{"value":371000,"currencyCode":"USD","timestamp":1451520000}],"quarterlyTaxProvision":[{"value":0,"currencyCode":"USD","timestamp":1419984000},{"value":0,"currencyCode":"USD","timestamp":1451520000},{"value":0,"currencyCode":"USD","timestamp":1475193600},{"value":-1901000,"currencyCode":"USD","timestamp":1483142400},{"value":384000,"currencyCode":"USD","timestamp":1506729600},{"value":448000,"currencyCode":"USD","timestamp":1514678400},{"value":52000,"currencyCode":"USD","timestamp":1522454400},{"value":557000,"currencyCode":"USD","timestamp":1530316800},{"value":521000,"currencyCode":"USD","timestamp":1538265600},{"value":553000,"currencyCode":"USD","timestamp":1546214400},{"value":24000,"currencyCode":"USD","timestamp":1553990400}],"trailingNetIncome":[{"value":589874000,"currencyCode":"USD","timestamp":1569801600}],"annualStockBasedCompensation":[{"value":1385000,"currencyCode":"USD","timestamp":1419984000},{"value":2342000,"currencyCode":"USD","timestamp":1451520000}],"quarterlyLongTermDebt":[{"value":0,"currencyCode":"USD","timestamp":1419984000},{"value":4119263000,"currencyCode":"USD","timestamp":1451520000},{"value":4120141000,"currencyCode":"USD","timestamp":1475193600},{"value":4121153000,"currencyCode":"USD","timestamp":1483142400},{"value":4122264000,"currencyCode":"USD","timestamp":1506729600},{"value":4123350000,"currencyCode":"USD","timestamp":1514678400},{"value":4124448000,"currencyCode":"USD","timestamp":1522454400},{"value":4125473000,"currencyCode":"USD","timestamp":1530316800}],"quarterlyNetPPE":[{"value":88831000,"currencyCode":"USD","timestamp":1419984000},{"value":88347000,"currencyCode":"USD","timestamp":1451520000},{"value":73739000,"currencyCode":"USD","timestamp":1475193600},{"value":73029000,"currencyCode":"USD","timestamp":1483142400},{"value":72287000,"currencyCode":"USD","timestamp":1506729600},{"value":10074218000,"currencyCode":"USD","timestamp":1514678400},{"value":10355681000,"currencyCode":"USD","timestamp":1522454400},{"value":11065809000,"currencyCode":"USD","timestamp":1530316800},{"value":11633284000,"currencyCode":"USD","timestamp":1538265600}],"quarterlyInventory":[{"value":371000,"currencyCode":"USD","timestamp":1419984000},{"value":528000,"currencyCode":"USD","timestamp":1451520000}],"quarterlyNonCurrentDeferredTaxesLiabilities":[{"value":5043000,"currencyCode":"USD","timestamp":1419984000},{"value":5043000,"currencyCode":"USD","timestamp":1451520000},{"value":3718000,"currencyCode":"USD","timestamp":1475193600},{"value":3718000,"currencyCode":"USD","timestamp":1483142400},{"value":4004000,"currencyCode":"USD","timestamp":1506729600},{"value":3340000,"currencyCode":"USD","timestamp":1514678400},{"value":3292000,"currencyCode":"USD","timestamp":1522454400},{"value":3011000,"currencyCode":"USD","timestamp":1530316800},{"value":3515000,"currencyCode":"USD","timestamp":1538265600}],"annualPurchaseOfInvestment":[{"value":0,"currencyCode":"USD","timestamp":1419984000},{"value":-1713818000,"currencyCode":"USD","timestamp":1451520000}],"annualCapitalStock":[{"value":3003000,"currencyCode":"USD","timestamp":1419984000},{"value":4047000,"currencyCode":"USD","timestamp":1451520000}],"quarterlyOtherIncomeExpense":[{"value":0,"currencyCode":"USD","timestamp":1419984000},{"value":0,"currencyCode":"USD","timestamp":1451520000},{"value":0,"currencyCode":"USD","timestamp":1475193600},{"value":-47527000,"currencyCode":"USD","timestamp":1483142400},{"value":-23040000,"currencyCode":"USD","timestamp":1506729600},{"value":-12334000,"currencyCode":"USD","timestamp":1514678400},{"value":-393000,"currencyCode":"USD","timestamp":1522454400},{"value":-889000,"currencyCode":"USD","timestamp":1530316800},{"value":-2867000,"currencyCode":"USD","timestamp":1538265600},{"value":-993000,"currencyCode":"USD","timestamp":1546214400}],"trailingOperatingCashFlow":[{"value":612764000,"currencyCode":"USD","timestamp":1569801600}],"quarterlyOtherCurrentLiabilities":[{"value":0,"currencyCode":"USD","timestamp":1419984000},{"value":0,"currencyCode":"USD","timestamp":1451520000}],"annualOperatingCashFlow":[{"value":3073000,"currencyCode":"USD","timestamp":1419984000},{"value":2888000,"currencyCode":"USD","timestamp":1451520000},{"value":2721000,"currencyCode":"USD","timestamp":1475193600},{"value":131684000,"currencyCode":"USD","timestamp":1483142400},{"value":504082000,"currencyCode":"USD","timestamp":1506729600}],"quarterlyCommonStockIssuance":[{"value":963782000,"currencyCode":"USD","timestamp":1419984000},{"value":0,"currencyCode":"USD","timestamp":1451520000},{"value":694374000,"currencyCode":"USD","timestamp":1475193600},{"value":128085000,"currencyCode":"USD","timestamp":1483142400},{"value":1036923000,"currencyCode":"USD","timestamp":1506729600},{"value":-648000,"currencyCode":"USD","timestamp":1514678400}],"annualDilutedAverageShares":[{"value":360778938,"currencyCode":"USD","timestamp":1419984000},{"value":360778938,"currencyCode":"USD","timestamp":1451520000},{"value":360778938,"currencyCode":"USD","timestamp":1475193600},{"value":327541414,"currencyCode":"USD","timestamp":1483142400},{"value":367316901,"currencyCode":"USD","timestamp":1506729600}],"annualCurrentLiabilities":[{"value":1224000,"currencyCode":"USD","timestamp":1419984000},{"value":1024000,"currencyCode":"USD","timestamp":1451520000},{"value":100274000,"currencyCode":"USD","timestamp":1475193600},{"value":162479000,"currencyCode":"USD","timestamp":1483142400}],"quarterlyChangeInCashSupplementalAsReported":[{"value":84000,"currencyCode":"USD","timestamp":1419984000},{"value":141635000,"currencyCode":"USD","timestamp":1451520000},{"value":-842000,"currencyCode":"USD","timestamp":1475193600},{"value":757984000,"currencyCode":"USD","timestamp":1483142400},{"value":-809267000,"currencyCode":"USD","timestamp":1506729600},{"value":453166000,"currencyCode":"USD","timestamp":1514678400},{"value":24195000,"currencyCode":"USD","timestamp":1522454400},{"value":610910000,"currencyCode":"USD","timestamp":1530316800},{"value":-770042000,"currencyCode":"USD","timestamp":1538265600}],"annualGrossProfit":[{"value":4841000,"currencyCode":"USD","timestamp":1419984000},{"value":4660000,"currencyCode":"USD","timestamp":1451520000},{"value":5046000,"currencyCode":"USD","timestamp":1475193600},{"value":167668000,"currencyCode":"USD","timestamp":1483142400},{"value":798796000,"currencyCode":"USD","timestamp":1506729600}],"quarterlyCostOfRevenue":[{"value":3047000,"currencyCode":"USD","timestamp":1419984000},{"value":3579000,"currencyCode":"USD","timestamp":1451520000},{"value":3008000,"currencyCode":"USD","timestamp":1475193600},{"value":23684000,"currencyCode":"USD","timestamp":1483142400},{"value":21338000,"currencyCode":"USD","timestamp":1506729600},{"value":23445000,"currencyCode":"USD","timestamp":1514678400},{"value":29646000,"currencyCode":"USD","timestamp":1522454400},{"value":24751000,"currencyCode":"USD","timestamp":1530316800},{"value":4092000,"currencyCode":"USD","timestamp":1538265600},{"value":4848000,"currencyCode":"USD","timestamp":1546214400},{"value":5423000,"currencyCode":"USD","timestamp":1553990400}],"quarterlyCurrentAccruedExpenses":[{"value":222000,"currencyCode":"USD","timestamp":1419984000},{"value":402000,"currencyCode":"USD","timestamp":1451520000},{"value":32150000,"currencyCode":"USD","timestamp":1475193600},{"value":19276000,"currencyCode":"USD","timestamp":1483142400},{"value":23672000,"currencyCode":"USD","timestamp":1506729600},{"value":45135000,"currencyCode":"USD","timestamp":1514678400},{"value":30310000,"currencyCode":"USD","timestamp":1522454400},{"value":31270000,"currencyCode":"USD","timestamp":1530316800},{"value":64735000,"currencyCode":"USD","timestamp":1538265600}],"annualEbitda":[{"value":2943000,"currencyCode":"USD","timestamp":1419984000},{"value":2900000,"currencyCode":"USD","timestamp":1451520000},{"value":3037000,"currencyCode":"USD","timestamp":1475193600},{"value":109143000,"currencyCode":"USD","timestamp":1483142400},{"value":749907000,"currencyCode":"USD","timestamp":1506729600}],"annualRepaymentOfDebt":[{"value":-226000,"currencyCode":"USD","timestamp":1419984000},{"value":-45000,"currencyCode":"USD","timestamp":1451520000},{"value":-51000,"currencyCode":"USD","timestamp":1475193600},{"value":-2350122000,"currencyCode":"USD","timestamp":1483142400},{"value":-690058000,"currencyCode":"USD","timestamp":1506729600}],"annualGainsLossesNotAffectingRetainedEarnings":[{"value":-22124000,"currencyCode":"USD","timestamp":1419984000}],"annualNetPPE":[{"value":90992000,"currencyCode":"USD","timestamp":1419984000},{"value":88831000,"currencyCode":"USD","timestamp":1451520000},{"value":147900000,"currencyCode":"USD","timestamp":1475193600},{"value":10074218000,"currencyCode":"USD","timestamp":1483142400}],"annualOtherNonCurrentLiabilities":[{"value":267000,"currencyCode":"USD","timestamp":1419984000},{"value":265000,"currencyCode":"USD","timestamp":1451520000},{"value":0,"currencyCode":"USD","timestamp":1475193600},{"value":62406000,"currencyCode":"USD","timestamp":1483142400}],"annualOtherIncomeExpense":[{"value":0,"currencyCode":"USD","timestamp":1419984000},{"value":0,"currencyCode":"USD","timestamp":1451520000},{"value":0,"currencyCode":"USD","timestamp":1475193600},{"value":-47527000,"currencyCode":"USD","timestamp":1483142400},{"value":-35767000,"currencyCode":"USD","timestamp":1506729600}],"quarterlyFreeCashFlow":[{"value":259000,"currencyCode":"USD","timestamp":1419984000},{"value":129389000,"currencyCode":"USD","timestamp":1451520000},{"value":843000,"currencyCode":"USD","timestamp":1475193600},{"value":245263000,"currencyCode":"USD","timestamp":1483142400},{"value":81667000,"currencyCode":"USD","timestamp":1506729600},{"value":168630000,"currencyCode":"USD","timestamp":1514678400},{"value":113966000,"currencyCode":"USD","timestamp":1522454400},{"value":146390000,"currencyCode":"USD","timestamp":1530316800},{"value":172410000,"currencyCode":"USD","timestamp":1538265600}],"quarterlyCapitalStock":[{"value":3701000,"currencyCode":"USD","timestamp":1419984000},{"value":3701000,"currencyCode":"USD","timestamp":1451520000},{"value":3702000,"currencyCode":"USD","timestamp":1475193600},{"value":4047000,"currencyCode":"USD","timestamp":1483142400},{"value":4110000,"currencyCode":"USD","timestamp":1506729600},{"value":4610000,"currencyCode":"USD","timestamp":1514678400},{"value":4610000,"currencyCode":"USD","timestamp":1522454400}],"trailingChangeInWorkingCapital":[{"value":-4743000,"currencyCode":"USD","timestamp":1569801600}],"trailingRepaymentOfDebt":[{"value":0,"currencyCode":"USD","timestamp":1569801600}],"quarterlyBeginningCashPosition":[{"value":836000,"currencyCode":"USD","timestamp":1419984000},{"value":55771000,"currencyCode":"USD","timestamp":1451520000},{"value":920000,"currencyCode":"USD","timestamp":1475193600},{"value":78000,"currencyCode":"USD","timestamp":1483142400},{"value":954548000,"currencyCode":"USD","timestamp":1506729600},{"value":145281000,"currencyCode":"USD","timestamp":1514678400},{"value":598447000,"currencyCode":"USD","timestamp":1522454400},{"value":622642000,"currencyCode":"USD","timestamp":1530316800},{"value":1233552000,"currencyCode":"USD","timestamp":1538265600}],"annualNetOtherInvestingChanges":[{"value":6000,"currencyCode":"USD","timestamp":1419984000},{"value":66000,"currencyCode":"USD","timestamp":1451520000},{"value":0,"currencyCode":"USD","timestamp":1475193600},{"value":-1136200000,"currencyCode":"USD","timestamp":1483142400},{"value":159000000,"currencyCode":"USD","timestamp":1506729600}],"trailingGrossProfit":[{"value":844186000,"currencyCode":"USD","timestamp":1569801600}],"annualOperatingIncome":[{"value":39000,"currencyCode":"USD","timestamp":1419984000},{"value":18000,"currencyCode":"USD","timestamp":1451520000},{"value":7000,"currencyCode":"USD","timestamp":1475193600},{"value":153235000,"currencyCode":"USD","timestamp":1483142400},{"value":770681000,"currencyCode":"USD","timestamp":1506729600}],"annualOtherCurrentLiabilities":[{"value":0,"currencyCode":"USD","timestamp":1419984000},{"value":0,"currencyCode":"USD","timestamp":1451520000},{"value":0,"currencyCode":"USD","timestamp":1475193600}],"annualChangeInCashSupplementalAsReported":[{"value":94000,"currencyCode":"USD","timestamp":1419984000},{"value":130000,"currencyCode":"USD","timestamp":1451520000},{"value":569000,"currencyCode":"USD","timestamp":1475193600},{"value":140799000,"currencyCode":"USD","timestamp":1483142400},{"value":401041000,"currencyCode":"USD","timestamp":1506729600}],"annualCashCashEquivalentsAndMarketableSecurities":[{"value":351000,"currencyCode":"USD","timestamp":1419984000},{"value":920000,"currencyCode":"USD","timestamp":1451520000},{"value":183646000,"currencyCode":"USD","timestamp":1475193600},{"value":1098760000,"currencyCode":"USD","timestamp":1483142400}],"annualCashFlowFromContinuingFinancingActivities":[{"value":-2968000,"currencyCode":"USD","timestamp":1419984000},{"value":-2026000,"currencyCode":"USD","timestamp":1451520000},{"value":-1283000,"currencyCode":"USD","timestamp":1475193600},{"value":1147284000,"currencyCode":"USD","timestamp":1483142400},{"value":1037836000,"currencyCode":"USD","timestamp":1506729600}],"trailingPretaxIncome":[{"value":599853000,"currencyCode":"USD","timestamp":1569801600}],"quarterlyNetIncomeCommonStockholders":[{"value":0,"currencyCode":"USD","timestamp":1419984000},{"value":0,"currencyCode":"USD","timestamp":1451520000},{"value":0,"currencyCode":"USD","timestamp":1475193600},{"value":42662000,"currencyCode":"USD","timestamp":1483142400},{"value":112122000,"currencyCode":"USD","timestamp":1506729600},{"value":139044000,"currencyCode":"USD","timestamp":1514678400},{"value":129912000,"currencyCode":"USD","timestamp":1522454400},{"value":142541000,"currencyCode":"USD","timestamp":1530316800},{"value":150849000,"currencyCode":"USD","timestamp":1538265600},{"value":152049000,"currencyCode":"USD","timestamp":1546214400},{"value":144435000,"currencyCode":"USD","timestamp":1553990400}],"annualNonCurrentDeferredRevenue":[{"value":43605000,"currencyCode":"USD","timestamp":1419984000}],"trailingInterestExpense":[{"value":231234000,"currencyCode":"USD","timestamp":1569801600}],"annualBasicEPS":[{"value":0.000011,"currencyCode":"USD","timestamp":1419984000},{"value":0.000008,"currencyCode":"USD","timestamp":1451520000},{"value":0,"currencyCode":"USD","timestamp":1475193600},{"value":0.130249,"currencyCode":"USD","timestamp":1483142400},{"value":1.43,"currencyCode":"USD","timestamp":1506729600}],"annualEndCashPosition":[{"value":221000,"currencyCode":"USD","timestamp":1419984000},{"value":351000,"currencyCode":"USD","timestamp":1451520000},{"value":920000,"currencyCode":"USD","timestamp":1475193600},{"value":197406000,"currencyCode":"USD","timestamp":1483142400},{"value":598447000,"currencyCode":"USD","timestamp":1506729600}],"quarterlyTotalAssets":[{"value":90475000,"currencyCode":"USD","timestamp":1419984000},{"value":89250000,"currencyCode":"USD","timestamp":1451520000},{"value":10486239000,"currencyCode":"USD","timestamp":1475193600},{"value":10564703000,"currencyCode":"USD","timestamp":1483142400},{"value":10568501000,"currencyCode":"USD","timestamp":1506729600},{"value":11333368000,"currencyCode":"USD","timestamp":1514678400},{"value":11448671000,"currencyCode":"USD","timestamp":1522454400},{"value":12522046000,"currencyCode":"USD","timestamp":1530316800},{"value":12581466000,"currencyCode":"USD","timestamp":1538265600}],"quarterlyTotalNonCurrentAssets":[{"value":88831000,"currencyCode":"USD","timestamp":1419984000},{"value":88347000,"currencyCode":"USD","timestamp":1451520000},{"value":9554216000,"currencyCode":"USD","timestamp":1475193600},{"value":9570249000,"currencyCode":"USD","timestamp":1483142400},{"value":10102544000,"currencyCode":"USD","timestamp":1506729600},{"value":10214044000,"currencyCode":"USD","timestamp":1514678400},{"value":10462143000,"currencyCode":"USD","timestamp":1522454400},{"value":11188356000,"currencyCode":"USD","timestamp":1530316800},{"value":11771661000,"currencyCode":"USD","timestamp":1538265600}],"trailingTotalRevenue":[{"value":883300000,"currencyCode":"USD","timestamp":1569801600}],"quarterlyCashCashEquivalentsAndMarketableSecurities":[{"value":920000,"currencyCode":"USD","timestamp":1419984000},{"value":84000,"currencyCode":"USD","timestamp":1451520000},{"value":918215000,"currencyCode":"USD","timestamp":1475193600},{"value":980646000,"currencyCode":"USD","timestamp":1483142400},{"value":465899000,"currencyCode":"USD","timestamp":1506729600},{"value":1098760000,"currencyCode":"USD","timestamp":1514678400},{"value":955154000,"currencyCode":"USD","timestamp":1522454400},{"value":1302921000,"currencyCode":"USD","timestamp":1530316800},{"value":774190000,"currencyCode":"USD","timestamp":1538265600}],"trailingPurchaseOfInvestment":[{"value":-2755520000,"currencyCode":"USD","timestamp":1569801600}],"quarterlyDilutedAverageShares":[{"value":360778938,"currencyCode":"USD","timestamp":1419984000},{"value":246224886,"currencyCode":"USD","timestamp":1451520000},{"value":227985982,"currencyCode":"USD","timestamp":1475193600},{"value":343056532,"currencyCode":"USD","timestamp":1483142400},{"value":369991738,"currencyCode":"USD","timestamp":1506729600},{"value":370127185,"currencyCode":"USD","timestamp":1514678400},{"value":385847082,"currencyCode":"USD","timestamp":1522454400},{"value":406035025,"currencyCode":"USD","timestamp":1530316800},{"value":412821400,"currencyCode":"USD","timestamp":1538265600},{"value":465771668,"currencyCode":"USD","timestamp":1546214400}],"trailingOtherIncomeExpense":[{"value":-5142000,"currencyCode":"USD","timestamp":1569801600}],"annualAccountsPayable":[{"value":342000,"currencyCode":"USD","timestamp":1419984000},{"value":305000,"currencyCode":"USD","timestamp":1451520000},{"value":5207000,"currencyCode":"USD","timestamp":1475193600},{"value":1057000,"currencyCode":"USD","timestamp":1483142400}],"trailingInvestingCashFlow":[{"value":-1664263000,"currencyCode":"USD","timestamp":1569801600}],"trailingCapitalExpenditure":[{"value":-7926000,"currencyCode":"USD","timestamp":1569801600}],"quarterlyCashAndCashEquivalents":[{"value":920000,"currencyCode":"USD","timestamp":1419984000},{"value":84000,"currencyCode":"USD","timestamp":1451520000},{"value":918215000,"currencyCode":"USD","timestamp":1475193600},{"value":940740000,"currencyCode":"USD","timestamp":1483142400},{"value":145223000,"currencyCode":"USD","timestamp":1506729600},{"value":577883000,"currencyCode":"USD","timestamp":1514678400},{"value":598276000,"currencyCode":"USD","timestamp":1522454400},{"value":1205335000,"currencyCode":"USD","timestamp":1530316800},{"value":431423000,"currencyCode":"USD","timestamp":1538265600}],"trailingChangeInCashSupplementalAsReported":[{"value":318229000,"currencyCode":"USD","timestamp":1569801600}],"quarterlyPurchaseOfInvestment":[{"value":-381528000,"currencyCode":"USD","timestamp":1419984000},{"value":-1292384000,"currencyCode":"USD","timestamp":1451520000},{"value":-289310000,"currencyCode":"USD","timestamp":1475193600},{"value":-779039000,"currencyCode":"USD","timestamp":1483142400},{"value":-902582000,"currencyCode":"USD","timestamp":1506729600}],"quarterlyInterestExpense":[{"value":1000,"currencyCode":"USD","timestamp":1419984000},{"value":1000,"currencyCode":"USD","timestamp":1451520000},{"value":0,"currencyCode":"USD","timestamp":1475193600},{"value":63354000,"currencyCode":"USD","timestamp":1483142400},{"value":52875000,"currencyCode":"USD","timestamp":1506729600},{"value":51440000,"currencyCode":"USD","timestamp":1514678400},{"value":54051000,"currencyCode":"USD","timestamp":1522454400},{"value":54298000,"currencyCode":"USD","timestamp":1530316800},{"value":53586000,"currencyCode":"USD","timestamp":1538265600},{"value":54819000,"currencyCode":"USD","timestamp":1546214400},{"value":68531000,"currencyCode":"USD","timestamp":1553990400}],"annualGrossPPE":[{"value":115759000,"currencyCode":"USD","timestamp":1419984000},{"value":116277000,"currencyCode":"USD","timestamp":1451520000},{"value":148651000,"currencyCode":"USD","timestamp":1475193600},{"value":10078655000,"currencyCode":"USD","timestamp":1483142400}],"trailingOperatingIncome":[{"value":816565000,"currencyCode":"USD","timestamp":1569801600}],"quarterlyCurrentDebt":[{"value":14000,"currencyCode":"USD","timestamp":1419984000},{"value":0,"currencyCode":"USD","timestamp":1451520000}],"trailingCashFlowFromContinuingFinancingActivities":[{"value":1369728000,"currencyCode":"USD","timestamp":1569801600}],"annualPretaxIncome":[{"value":0,"currencyCode":"USD","timestamp":1419984000},{"value":0,"currencyCode":"USD","timestamp":1451520000},{"value":0,"currencyCode":"USD","timestamp":1475193600},{"value":42636000,"currencyCode":"USD","timestamp":1483142400},{"value":533558000,"currencyCode":"USD","timestamp":1506729600}],"quarterlySaleOfInvestment":[{"value":320676000,"currencyCode":"USD","timestamp":1419984000},{"value":188782000,"currencyCode":"USD","timestamp":1451520000},{"value":332095000,"currencyCode":"USD","timestamp":1475193600},{"value":97586000,"currencyCode":"USD","timestamp":1483142400}],"quarterlyChangesInAccountReceivables":[{"value":-109000,"currencyCode":"USD","timestamp":1419984000}],"quarterlyDepreciationAndAmortization":[{"value":803000,"currencyCode":"USD","timestamp":1419984000},{"value":751000,"currencyCode":"USD","timestamp":1451520000},{"value":805000,"currencyCode":"USD","timestamp":1475193600},{"value":1023000,"currencyCode":"USD","timestamp":1483142400},{"value":929000,"currencyCode":"USD","timestamp":1506729600},{"value":929000,"currencyCode":"USD","timestamp":1514678400},{"value":930000,"currencyCode":"USD","timestamp":1522454400},{"value":1018000,"currencyCode":"USD","timestamp":1530316800},{"value":1000000,"currencyCode":"USD","timestamp":1538265600}],"trailingEndCashPosition":[{"value":463510000,"currencyCode":"USD","timestamp":1569801600}],"annualInvestmentsAndAdvances":[{"value":8268643000,"currencyCode":"USD","timestamp":1419984000},{"value":8916047000,"currencyCode":"USD","timestamp":1451520000}],"quarterlyTotalLiabilitiesNetMinorityInterest":[{"value":6332000,"currencyCode":"USD","timestamp":1419984000},{"value":6255000,"currencyCode":"USD","timestamp":1451520000},{"value":4351339000,"currencyCode":"USD","timestamp":1475193600},{"value":4391760000,"currencyCode":"USD","timestamp":1483142400},{"value":4361228000,"currencyCode":"USD","timestamp":1506729600},{"value":4432346000,"currencyCode":"USD","timestamp":1514678400},{"value":4402783000,"currencyCode":"USD","timestamp":1522454400},{"value":4449623000,"currencyCode":"USD","timestamp":1530316800},{"value":4507397000,"currencyCode":"USD","timestamp":1538265600}],"quarterlyAccountsPayable":[{"value":305000,"currencyCode":"USD","timestamp":1419984000},{"value":194000,"currencyCode":"USD","timestamp":1451520000},{"value":2458000,"currencyCode":"USD","timestamp":1475193600},{"value":1317000,"currencyCode":"USD","timestamp":1483142400},{"value":1057000,"currencyCode":"USD","timestamp":1506729600},{"value":1227000,"currencyCode":"USD","timestamp":1514678400},{"value":451000,"currencyCode":"USD","timestamp":1522454400},{"value":1307000,"currencyCode":"USD","timestamp":1530316800}],"quarterlyGrossProfit":[{"value":1236000,"currencyCode":"USD","timestamp":1419984000},{"value":1244000,"currencyCode":"USD","timestamp":1451520000},{"value":1094000,"currencyCode":"USD","timestamp":1475193600},{"value":163925000,"currencyCode":"USD","timestamp":1483142400},{"value":196938000,"currencyCode":"USD","timestamp":1506729600},{"value":197530000,"currencyCode":"USD","timestamp":1514678400},{"value":203041000,"currencyCode":"USD","timestamp":1522454400},{"value":201288000,"currencyCode":"USD","timestamp":1530316800},{"value":209910000,"currencyCode":"USD","timestamp":1538265600},{"value":215898000,"currencyCode":"USD","timestamp":1546214400},{"value":217090000,"currencyCode":"USD","timestamp":1553990400}],"annualAccumulatedDepreciation":[{"value":-24767000,"currencyCode":"USD","timestamp":1419984000},{"value":-27446000,"currencyCode":"USD","timestamp":1451520000},{"value":-751000,"currencyCode":"USD","timestamp":1475193600},{"value":-4437000,"currencyCode":"USD","timestamp":1483142400}],"quarterlyChangeInWorkingCapital":[{"value":-316000,"currencyCode":"USD","timestamp":1419984000},{"value":84523000,"currencyCode":"USD","timestamp":1451520000},{"value":92000,"currencyCode":"USD","timestamp":1475193600},{"value":-37601000,"currencyCode":"USD","timestamp":1483142400},{"value":-65551000,"currencyCode":"USD","timestamp":1506729600},{"value":73399000,"currencyCode":"USD","timestamp":1514678400},{"value":-38218000,"currencyCode":"USD","timestamp":1522454400},{"value":-8833000,"currencyCode":"USD","timestamp":1530316800},{"value":8028000,"currencyCode":"USD","timestamp":1538265600}],"annualSellingGeneralAndAdministration":[{"value":1898000,"currencyCode":"USD","timestamp":1419984000},{"value":1760000,"currencyCode":"USD","timestamp":1451520000},{"value":2009000,"currencyCode":"USD","timestamp":1475193600},{"value":11280000,"currencyCode":"USD","timestamp":1483142400},{"value":24429000,"currencyCode":"USD","timestamp":1506729600}],"quarterlyNonCurrentDeferredRevenue":[{"value":71961000,"currencyCode":"USD","timestamp":1419984000},{"value":701000,"currencyCode":"USD","timestamp":1451520000},{"value":43605000,"currencyCode":"USD","timestamp":1475193600},{"value":355000,"currencyCode":"USD","timestamp":1483142400},{"value":5000,"currencyCode":"USD","timestamp":1506729600},{"value":250000,"currencyCode":"USD","timestamp":1514678400}],"quarterlyChangeInAccountPayable":[{"value":-153000,"currencyCode":"USD","timestamp":1419984000},{"value":214000,"currencyCode":"USD","timestamp":1451520000}],"quarterlyDeferredIncomeTax":[{"value":-1912000,"currencyCode":"USD","timestamp":1419984000}],"trailingNetIncomeContinuousOperations":[{"value":598198000,"currencyCode":"USD","timestamp":1569801600}],"annualOtherNonCurrentAssets":[{"value":0,"currencyCode":"USD","timestamp":1419984000},{"value":0,"currencyCode":"USD","timestamp":1451520000},{"value":1125763000,"currencyCode":"USD","timestamp":1475193600},{"value":44037000,"currencyCode":"USD","timestamp":1483142400}],"trailingSellingGeneralAndAdministration":[{"value":23744000,"currencyCode":"USD","timestamp":1569801600}],"quarterlyGainsLossesNotAffectingRetainedEarnings":[{"value":-4640000,"currencyCode":"USD","timestamp":1419984000},{"value":5465000,"currencyCode":"USD","timestamp":1451520000},{"value":-22124000,"currencyCode":"USD","timestamp":1475193600},{"value":-39315000,"currencyCode":"USD","timestamp":1483142400},{"value":-70003000,"currencyCode":"USD","timestamp":1506729600},{"value":-77116000,"currencyCode":"USD","timestamp":1514678400}],"annualOperatingExpense":[{"value":4802000,"currencyCode":"USD","timestamp":1419984000},{"value":4642000,"currencyCode":"USD","timestamp":1451520000},{"value":5039000,"currencyCode":"USD","timestamp":1475193600},{"value":14433000,"currencyCode":"USD","timestamp":1483142400},{"value":28115000,"currencyCode":"USD","timestamp":1506729600}],"trailingOperatingExpense":[{"value":27621000,"currencyCode":"USD","timestamp":1569801600}],"trailingNetOtherFinancingCharges":[{"value":-15761000,"currencyCode":"USD","timestamp":1569801600}],"annualNetIncomeContinuousOperations":[{"value":4000,"currencyCode":"USD","timestamp":1419984000},{"value":3000,"currencyCode":"USD","timestamp":1451520000},{"value":0,"currencyCode":"USD","timestamp":1475193600},{"value":44537000,"currencyCode":"USD","timestamp":1483142400},{"value":532117000,"currencyCode":"USD","timestamp":1506729600}],"annualCurrentAccruedExpenses":[{"value":329000,"currencyCode":"USD","timestamp":1419984000},{"value":222000,"currencyCode":"USD","timestamp":1451520000},{"value":24391000,"currencyCode":"USD","timestamp":1475193600},{"value":45135000,"currencyCode":"USD","timestamp":1483142400}],"annualCapitalExpenditure":[{"value":-17000,"currencyCode":"USD","timestamp":1419984000},{"value":-798000,"currencyCode":"USD","timestamp":1451520000},{"value":-869000,"currencyCode":"USD","timestamp":1475193600},{"value":-1969000,"currencyCode":"USD","timestamp":1483142400},{"value":-7679000,"currencyCode":"USD","timestamp":1506729600}],"annualCashAndCashEquivalents":[{"value":351000,"currencyCode":"USD","timestamp":1419984000},{"value":920000,"currencyCode":"USD","timestamp":1451520000},{"value":183646000,"currencyCode":"USD","timestamp":1475193600},{"value":577883000,"currencyCode":"USD","timestamp":1483142400}],"quarterlyGrossPPE":[{"value":116277000,"currencyCode":"USD","timestamp":1419984000},{"value":117520000,"currencyCode":"USD","timestamp":1451520000},{"value":75396000,"currencyCode":"USD","timestamp":1475193600},{"value":75608000,"currencyCode":"USD","timestamp":1483142400},{"value":75795000,"currencyCode":"USD","timestamp":1506729600},{"value":10078655000,"currencyCode":"USD","timestamp":1514678400},{"value":10361046000,"currencyCode":"USD","timestamp":1522454400},{"value":11072194000,"currencyCode":"USD","timestamp":1530316800},{"value":11633284000,"currencyCode":"USD","timestamp":1538265600}],"quarterlyOperatingIncome":[{"value":1000,"currencyCode":"USD","timestamp":1419984000},{"value":1000,"currencyCode":"USD","timestamp":1451520000},{"value":0,"currencyCode":"USD","timestamp":1475193600},{"value":153235000,"currencyCode":"USD","timestamp":1483142400},{"value":188724000,"currencyCode":"USD","timestamp":1506729600},{"value":189448000,"currencyCode":"USD","timestamp":1514678400},{"value":196434000,"currencyCode":"USD","timestamp":1522454400},{"value":196075000,"currencyCode":"USD","timestamp":1530316800},{"value":202755000,"currencyCode":"USD","timestamp":1538265600},{"value":208362000,"currencyCode":"USD","timestamp":1546214400},{"value":209373000,"currencyCode":"USD","timestamp":1553990400}],"quarterlyTotalRevenue":[{"value":4283000,"currencyCode":"USD","timestamp":1419984000},{"value":4823000,"currencyCode":"USD","timestamp":1451520000},{"value":4102000,"currencyCode":"USD","timestamp":1475193600},{"value":187609000,"currencyCode":"USD","timestamp":1483142400},{"value":218276000,"currencyCode":"USD","timestamp":1506729600},{"value":220975000,"currencyCode":"USD","timestamp":1514678400},{"value":232687000,"currencyCode":"USD","timestamp":1522454400},{"value":226039000,"currencyCode":"USD","timestamp":1530316800},{"value":214002000,"currencyCode":"USD","timestamp":1538265600},{"value":220746000,"currencyCode":"USD","timestamp":1546214400},{"value":222513000,"currencyCode":"USD","timestamp":1553990400}],"quarterlyChangeInInventory":[{"value":80000,"currencyCode":"USD","timestamp":1419984000},{"value":-69000,"currencyCode":"USD","timestamp":1451520000}],"quarterlyInvestingCashFlow":[{"value":-76000,"currencyCode":"USD","timestamp":1419984000},{"value":-1136251000,"currencyCode":"USD","timestamp":1451520000},{"value":-66000,"currencyCode":"USD","timestamp":1475193600},{"value":-40397000,"currencyCode":"USD","timestamp":1483142400},{"value":-792008000,"currencyCode":"USD","timestamp":1506729600},{"value":-308406000,"currencyCode":"USD","timestamp":1514678400},{"value":-101160000,"currencyCode":"USD","timestamp":1522454400},{"value":-447854000,"currencyCode":"USD","timestamp":1530316800},{"value":-806843000,"currencyCode":"USD","timestamp":1538265600}],"annualInterestExpense":[{"value":39000,"currencyCode":"USD","timestamp":1419984000},{"value":18000,"currencyCode":"USD","timestamp":1451520000},{"value":7000,"currencyCode":"USD","timestamp":1475193600},{"value":63354000,"currencyCode":"USD","timestamp":1483142400},{"value":212663000,"currencyCode":"USD","timestamp":1506729600}],"quarterlyBasicEPS":[{"value":0,"currencyCode":"USD","timestamp":1419984000},{"value":0,"currencyCode":"USD","timestamp":1451520000},{"value":0.19,"currencyCode":"USD","timestamp":1475193600},{"value":0.33,"currencyCode":"USD","timestamp":1483142400},{"value":0.375863,"currencyCode":"USD","timestamp":1506729600},{"value":0.35,"currencyCode":"USD","timestamp":1514678400},{"value":0.37,"currencyCode":"USD","timestamp":1522454400},{"value":0.37,"currencyCode":"USD","timestamp":1530316800},{"value":0.37,"currencyCode":"USD","timestamp":1538265600},{"value":0.31,"currencyCode":"USD","timestamp":1546214400}],"trailingBeginningCashPosition":[{"value":145281000,"currencyCode":"USD","timestamp":1569801600}],"trailingCostOfRevenue":[{"value":39114000,"currencyCode":"USD","timestamp":1569801600}],"annualTotalRevenue":[{"value":18908000,"currencyCode":"USD","timestamp":1419984000},{"value":18077000,"currencyCode":"USD","timestamp":1451520000},{"value":18785000,"currencyCode":"USD","timestamp":1475193600},{"value":201436000,"currencyCode":"USD","timestamp":1483142400},{"value":897977000,"currencyCode":"USD","timestamp":1506729600}],"annualCurrentAssets":[{"value":1042000,"currencyCode":"USD","timestamp":1419984000},{"value":1644000,"currencyCode":"USD","timestamp":1451520000},{"value":197406000,"currencyCode":"USD","timestamp":1475193600},{"value":1119324000,"currencyCode":"USD","timestamp":1483142400}],"annualChangeInAccountPayable":[{"value":419000,"currencyCode":"USD","timestamp":1419984000},{"value":52000,"currencyCode":"USD","timestamp":1451520000},{"value":-39000,"currencyCode":"USD","timestamp":1475193600}],"annualTotalNonCurrentLiabilitiesNetMinorityInterest":[{"value":5435000,"currencyCode":"USD","timestamp":1419984000},{"value":5308000,"currencyCode":"USD","timestamp":1451520000},{"value":4863074000,"currencyCode":"USD","timestamp":1475193600},{"value":4269867000,"currencyCode":"USD","timestamp":1483142400}],"annualNetIncomeCommonStockholders":[{"value":4000,"currencyCode":"USD","timestamp":1419984000},{"value":3000,"currencyCode":"USD","timestamp":1451520000},{"value":0,"currencyCode":"USD","timestamp":1475193600},{"value":42662000,"currencyCode":"USD","timestamp":1483142400},{"value":523619000,"currencyCode":"USD","timestamp":1506729600}],"quarterlyOtherNonCashItems":[{"value":-41000,"currencyCode":"USD","timestamp":1419984000},{"value":1541000,"currencyCode":"USD","timestamp":1451520000},{"value":-1047000,"currencyCode":"USD","timestamp":1475193600},{"value":-378000,"currencyCode":"USD","timestamp":1483142400},{"value":17310000,"currencyCode":"USD","timestamp":1506729600}],"quarterlyStockBasedCompensation":[{"value":1385000,"currencyCode":"USD","timestamp":1419984000},{"value":623000,"currencyCode":"USD","timestamp":1451520000},{"value":860000,"currencyCode":"USD","timestamp":1475193600},{"value":1051000,"currencyCode":"USD","timestamp":1483142400},{"value":1366000,"currencyCode":"USD","timestamp":1506729600},{"value":1404000,"currencyCode":"USD","timestamp":1514678400}],"quarterlyEndCashPosition":[{"value":920000,"currencyCode":"USD","timestamp":1419984000},{"value":197406000,"currencyCode":"USD","timestamp":1451520000},{"value":78000,"currencyCode":"USD","timestamp":1475193600},{"value":954548000,"currencyCode":"USD","timestamp":1483142400},{"value":145281000,"currencyCode":"USD","timestamp":1506729600},{"value":598447000,"currencyCode":"USD","timestamp":1514678400},{"value":622642000,"currencyCode":"USD","timestamp":1522454400},{"value":1233552000,"currencyCode":"USD","timestamp":1530316800},{"value":463510000,"currencyCode":"USD","timestamp":1538265600}],"annualNetOtherFinancingCharges":[{"value":-2742000,"currencyCode":"USD","timestamp":1419984000},{"value":-1981000,"currencyCode":"USD","timestamp":1451520000},{"value":-1232000,"currencyCode":"USD","timestamp":1475193600},{"value":40938000,"currencyCode":"USD","timestamp":1483142400},{"value":-10917000,"currencyCode":"USD","timestamp":1506729600}],"quarterlyBasicAverageShares":[{"value":360778938,"currencyCode":"USD","timestamp":1419984000},{"value":246224886,"currencyCode":"USD","timestamp":1451520000},{"value":227828844,"currencyCode":"USD","timestamp":1475193600},{"value":342900842,"currencyCode":"USD","timestamp":1483142400},{"value":369932843,"currencyCode":"USD","timestamp":1506729600},{"value":369935055,"currencyCode":"USD","timestamp":1514678400},{"value":385720716,"currencyCode":"USD","timestamp":1522454400},{"value":405733656,"currencyCode":"USD","timestamp":1530316800},{"value":412309577,"currencyCode":"USD","timestamp":1538265600},{"value":460666295,"currencyCode":"USD","timestamp":1546214400}],"annualCommonStockIssuance":[{"value":963782000,"currencyCode":"USD","timestamp":1419984000},{"value":2001493000,"currencyCode":"USD","timestamp":1451520000}],"annualOtherShortTermInvestments":[{"value":520877000,"currencyCode":"USD","timestamp":1419984000}],"quarterlyEbitda":[{"value":777000,"currencyCode":"USD","timestamp":1419984000},{"value":804000,"currencyCode":"USD","timestamp":1451520000},{"value":801000,"currencyCode":"USD","timestamp":1475193600},{"value":106741000,"currencyCode":"USD","timestamp":1483142400},{"value":168268000,"currencyCode":"USD","timestamp":1506729600},{"value":194270000,"currencyCode":"USD","timestamp":1514678400},{"value":187056000,"currencyCode":"USD","timestamp":1522454400},{"value":200414000,"currencyCode":"USD","timestamp":1530316800},{"value":207963000,"currencyCode":"USD","timestamp":1538265600},{"value":210517000,"currencyCode":"USD","timestamp":1546214400},{"value":216070000,"currencyCode":"USD","timestamp":1553990400}],"annualDeferredIncomeTax":[{"value":-91000,"currencyCode":"USD","timestamp":1419984000},{"value":-101000,"currencyCode":"USD","timestamp":1451520000},{"value":-111000,"currencyCode":"USD","timestamp":1475193600},{"value":-1912000,"currencyCode":"USD","timestamp":1483142400},{"value":-348000,"currencyCode":"USD","timestamp":1506729600}],"quarterlyCashDividendsPaid":[{"value":-116341000,"currencyCode":"USD","timestamp":1419984000},{"value":-118077000,"currencyCode":"USD","timestamp":1451520000},{"value":-132441000,"currencyCode":"USD","timestamp":1475193600}],"quarterlyTotalNonCurrentLiabilitiesNetMinorityInterest":[{"value":5308000,"currencyCode":"USD","timestamp":1419984000},{"value":5292000,"currencyCode":"USD","timestamp":1451520000},{"value":4122981000,"currencyCode":"USD","timestamp":1475193600},{"value":4274060000,"currencyCode":"USD","timestamp":1483142400},{"value":4231200000,"currencyCode":"USD","timestamp":1506729600},{"value":4269867000,"currencyCode":"USD","timestamp":1514678400},{"value":4253190000,"currencyCode":"USD","timestamp":1522454400},{"value":4285461000,"currencyCode":"USD","timestamp":1530316800},{"value":4304307000,"currencyCode":"USD","timestamp":1538265600}],"annualFreeCashFlow":[{"value":3056000,"currencyCode":"USD","timestamp":1419984000},{"value":2090000,"currencyCode":"USD","timestamp":1451520000},{"value":1852000,"currencyCode":"USD","timestamp":1475193600},{"value":129715000,"currencyCode":"USD","timestamp":1483142400},{"value":496403000,"currencyCode":"USD","timestamp":1506729600}],"annualChangeInWorkingCapital":[{"value":253000,"currencyCode":"USD","timestamp":1419984000},{"value":111000,"currencyCode":"USD","timestamp":1451520000},{"value":-188000,"currencyCode":"USD","timestamp":1475193600},{"value":84354000,"currencyCode":"USD","timestamp":1483142400},{"value":-29661000,"currencyCode":"USD","timestamp":1506729600}],"quarterlyPretaxIncome":[{"value":0,"currencyCode":"USD","timestamp":1419984000},{"value":0,"currencyCode":"USD","timestamp":1451520000},{"value":0,"currencyCode":"USD","timestamp":1475193600},{"value":42636000,"currencyCode":"USD","timestamp":1483142400},{"value":114487000,"currencyCode":"USD","timestamp":1506729600},{"value":141807000,"currencyCode":"USD","timestamp":1514678400},{"value":132076000,"currencyCode":"USD","timestamp":1522454400},{"value":145187000,"currencyCode":"USD","timestamp":1530316800},{"value":153447000,"currencyCode":"USD","timestamp":1538265600},{"value":154680000,"currencyCode":"USD","timestamp":1546214400},{"value":146539000,"currencyCode":"USD","timestamp":1553990400}],"quarterlyOperatingExpense":[{"value":1235000,"currencyCode":"USD","timestamp":1419984000},{"value":1243000,"currencyCode":"USD","timestamp":1451520000},{"value":1094000,"currencyCode":"USD","timestamp":1475193600},{"value":10690000,"currencyCode":"USD","timestamp":1483142400},{"value":8214000,"currencyCode":"USD","timestamp":1506729600},{"value":8082000,"currencyCode":"USD","timestamp":1514678400},{"value":6607000,"currencyCode":"USD","timestamp":1522454400},{"value":5213000,"currencyCode":"USD","timestamp":1530316800},{"value":7155000,"currencyCode":"USD","timestamp":1538265600},{"value":7536000,"currencyCode":"USD","timestamp":1546214400},{"value":7717000,"currencyCode":"USD","timestamp":1553990400}],"quarterlyOtherShortTermInvestments":[{"value":39906000,"currencyCode":"USD","timestamp":1419984000},{"value":320676000,"currencyCode":"USD","timestamp":1451520000},{"value":520877000,"currencyCode":"USD","timestamp":1475193600},{"value":356878000,"currencyCode":"USD","timestamp":1483142400},{"value":97586000,"currencyCode":"USD","timestamp":1506729600},{"value":342767000,"currencyCode":"USD","timestamp":1514678400}],"quarterlyRetainedEarnings":[{"value":52000,"currencyCode":"USD","timestamp":1419984000},{"value":52000,"currencyCode":"USD","timestamp":1451520000},{"value":95563000,"currencyCode":"USD","timestamp":1475193600},{"value":137444000,"currencyCode":"USD","timestamp":1483142400},{"value":160915000,"currencyCode":"USD","timestamp":1506729600},{"value":187096000,"currencyCode":"USD","timestamp":1514678400},{"value":219791000,"currencyCode":"USD","timestamp":1522454400},{"value":239301000,"currencyCode":"USD","timestamp":1530316800},{"value":246587000,"currencyCode":"USD","timestamp":1538265600}],"quarterlyCurrentDeferredRevenue":[{"value":125000,"currencyCode":"USD","timestamp":1419984000},{"value":51000,"currencyCode":"USD","timestamp":1451520000},{"value":60929000,"currencyCode":"USD","timestamp":1475193600}],"trailingNetIncomeCommonStockholders":[{"value":589874000,"currencyCode":"USD","timestamp":1569801600}],"quarterlyCurrentAssets":[{"value":1644000,"currencyCode":"USD","timestamp":1419984000},{"value":903000,"currencyCode":"USD","timestamp":1451520000},{"value":932023000,"currencyCode":"USD","timestamp":1475193600},{"value":994454000,"currencyCode":"USD","timestamp":1483142400},{"value":465957000,"currencyCode":"USD","timestamp":1506729600},{"value":1119324000,"currencyCode":"USD","timestamp":1514678400},{"value":986528000,"currencyCode":"USD","timestamp":1522454400},{"value":1333690000,"currencyCode":"USD","timestamp":1530316800},{"value":809805000,"currencyCode":"USD","timestamp":1538265600}],"quarterlySellingGeneralAndAdministration":[{"value":459000,"currencyCode":"USD","timestamp":1419984000},{"value":440000,"currencyCode":"USD","timestamp":1451520000},{"value":293000,"currencyCode":"USD","timestamp":1475193600},{"value":9939000,"currencyCode":"USD","timestamp":1483142400},{"value":7308000,"currencyCode":"USD","timestamp":1506729600},{"value":7160000,"currencyCode":"USD","timestamp":1514678400},{"value":5678000,"currencyCode":"USD","timestamp":1522454400},{"value":4284000,"currencyCode":"USD","timestamp":1530316800},{"value":6225000,"currencyCode":"USD","timestamp":1538265600},{"value":6518000,"currencyCode":"USD","timestamp":1546214400},{"value":6717000,"currencyCode":"USD","timestamp":1553990400}],"annualRetainedEarnings":[{"value":52000,"currencyCode":"USD","timestamp":1419984000},{"value":52000,"currencyCode":"USD","timestamp":1451520000},{"value":42662000,"currencyCode":"USD","timestamp":1475193600},{"value":187096000,"currencyCode":"USD","timestamp":1483142400}],"quarterlyStockholdersEquity":[{"value":84143000,"currencyCode":"USD","timestamp":1419984000},{"value":82995000,"currencyCode":"USD","timestamp":1451520000},{"value":6051900000,"currencyCode":"USD","timestamp":1475193600},{"value":6089609000,"currencyCode":"USD","timestamp":1483142400},{"value":6123808000,"currencyCode":"USD","timestamp":1506729600},{"value":6817449000,"currencyCode":"USD","timestamp":1514678400},{"value":6962269000,"currencyCode":"USD","timestamp":1522454400},{"value":7988737000,"currencyCode":"USD","timestamp":1530316800},{"value":7990314000,"currencyCode":"USD","timestamp":1538265600}],"quarterlyCurrentLiabilities":[{"value":1024000,"currencyCode":"USD","timestamp":1419984000},{"value":963000,"currencyCode":"USD","timestamp":1451520000},{"value":228358000,"currencyCode":"USD","timestamp":1475193600},{"value":117700000,"currencyCode":"USD","timestamp":1483142400},{"value":130028000,"currencyCode":"USD","timestamp":1506729600},{"value":162479000,"currencyCode":"USD","timestamp":1514678400},{"value":149593000,"currencyCode":"USD","timestamp":1522454400},{"value":164162000,"currencyCode":"USD","timestamp":1530316800},{"value":203090000,"currencyCode":"USD","timestamp":1538265600}],"annualTotalAssets":[{"value":92034000,"currencyCode":"USD","timestamp":1419984000},{"value":90475000,"currencyCode":"USD","timestamp":1451520000},{"value":9739712000,"currencyCode":"USD","timestamp":1475193600},{"value":11333368000,"currencyCode":"USD","timestamp":1483142400}],"quarterlyDilutedEPS":[{"value":0,"currencyCode":"USD","timestamp":1419984000},{"value":0,"currencyCode":"USD","timestamp":1451520000},{"value":0.19,"currencyCode":"USD","timestamp":1475193600},{"value":0.33,"currencyCode":"USD","timestamp":1483142400},{"value":0.375803,"currencyCode":"USD","timestamp":1506729600},{"value":0.35,"currencyCode":"USD","timestamp":1514678400},{"value":0.37,"currencyCode":"USD","timestamp":1522454400},{"value":0.37,"currencyCode":"USD","timestamp":1530316800},{"value":0.37,"currencyCode":"USD","timestamp":1538265600},{"value":0.31,"currencyCode":"USD","timestamp":1546214400}],"trailingCommonStockIssuance":[{"value":1858734000,"currencyCode":"USD","timestamp":1569801600}],"quarterlyNetOtherInvestingChanges":[{"value":0,"currencyCode":"USD","timestamp":1419984000},{"value":-1136200000,"currencyCode":"USD","timestamp":1451520000},{"value":670237000,"currencyCode":"USD","timestamp":1475193600}],"trailingFreeCashFlow":[{"value":604838000,"currencyCode":"USD","timestamp":1569801600}],"annualTotalLiabilitiesNetMinorityInterest":[{"value":6659000,"currencyCode":"USD","timestamp":1419984000},{"value":6332000,"currencyCode":"USD","timestamp":1451520000},{"value":4963348000,"currencyCode":"USD","timestamp":1475193600},{"value":4432346000,"currencyCode":"USD","timestamp":1483142400}],"quarterlyOtherCurrentAssets":[{"value":0,"currencyCode":"USD","timestamp":1419984000},{"value":0,"currencyCode":"USD","timestamp":1451520000}],"annualTaxProvision":[{"value":-4000,"currencyCode":"USD","timestamp":1419984000},{"value":-3000,"currencyCode":"USD","timestamp":1451520000},{"value":0,"currencyCode":"USD","timestamp":1475193600},{"value":-1901000,"currencyCode":"USD","timestamp":1483142400},{"value":1441000,"currencyCode":"USD","timestamp":1506729600}],"annualNetIncome":[{"value":4000,"currencyCode":"USD","timestamp":1419984000},{"value":3000,"currencyCode":"USD","timestamp":1451520000},{"value":0,"currencyCode":"USD","timestamp":1475193600},{"value":42662000,"currencyCode":"USD","timestamp":1483142400},{"value":523619000,"currencyCode":"USD","timestamp":1506729600}],"quarterlyAccumulatedDepreciation":[{"value":-27446000,"currencyCode":"USD","timestamp":1419984000},{"value":-29173000,"currencyCode":"USD","timestamp":1451520000},{"value":-1657000,"currencyCode":"USD","timestamp":1475193600},{"value":-2579000,"currencyCode":"USD","timestamp":1483142400},{"value":-3508000,"currencyCode":"USD","timestamp":1506729600},{"value":-4437000,"currencyCode":"USD","timestamp":1514678400},{"value":-5365000,"currencyCode":"USD","timestamp":1522454400},{"value":-6385000,"currencyCode":"USD","timestamp":1530316800}],"quarterlyRepaymentOfDebt":[{"value":-13000,"currencyCode":"USD","timestamp":1419984000},{"value":-2350108000,"currencyCode":"USD","timestamp":1451520000},{"value":-14000,"currencyCode":"USD","timestamp":1475193600},{"value":-690044000,"currencyCode":"USD","timestamp":1483142400},{"value":0,"currencyCode":"USD","timestamp":1506729600},{"value":0,"currencyCode":"USD","timestamp":1514678400},{"value":0,"currencyCode":"USD","timestamp":1522454400},{"value":0,"currencyCode":"USD","timestamp":1530316800},{"value":0,"currencyCode":"USD","timestamp":1538265600}],"annualCashDividendsPaid":[{"value":-262682000,"currencyCode":"USD","timestamp":1419984000}],"annualCurrentDebt":[{"value":51000,"currencyCode":"USD","timestamp":1419984000},{"value":14000,"currencyCode":"USD","timestamp":1451520000}],"annualBeginningCashPosition":[{"value":127000,"currencyCode":"USD","timestamp":1419984000},{"value":221000,"currencyCode":"USD","timestamp":1451520000},{"value":351000,"currencyCode":"USD","timestamp":1475193600},{"value":920000,"currencyCode":"USD","timestamp":1483142400},{"value":197406000,"currencyCode":"USD","timestamp":1506729600}],"annualLongTermDebt":[{"value":14000,"currencyCode":"USD","timestamp":1419984000},{"value":0,"currencyCode":"USD","timestamp":1451520000},{"value":4785756000,"currencyCode":"USD","timestamp":1475193600},{"value":4122264000,"currencyCode":"USD","timestamp":1483142400}],"annualOtherCurrentAssets":[{"value":12000,"currencyCode":"USD","timestamp":1419984000},{"value":0,"currencyCode":"USD","timestamp":1451520000},{"value":0,"currencyCode":"USD","timestamp":1475193600}],"annualCurrentDeferredRevenue":[{"value":114000,"currencyCode":"USD","timestamp":1419984000},{"value":125000,"currencyCode":"USD","timestamp":1451520000},{"value":68117000,"currencyCode":"USD","timestamp":1475193600}],"annualCostOfRevenue":[{"value":14067000,"currencyCode":"USD","timestamp":1419984000},{"value":13417000,"currencyCode":"USD","timestamp":1451520000},{"value":13739000,"currencyCode":"USD","timestamp":1475193600},{"value":33768000,"currencyCode":"USD","timestamp":1483142400},{"value":99181000,"currencyCode":"USD","timestamp":1506729600}],"annualTotalNonCurrentAssets":[{"value":90992000,"currencyCode":"USD","timestamp":1419984000},{"value":88831000,"currencyCode":"USD","timestamp":1451520000},{"value":9542306000,"currencyCode":"USD","timestamp":1475193600},{"value":10214044000,"currencyCode":"USD","timestamp":1483142400}],"trailingDepreciationAndAmortization":[{"value":3877000,"currencyCode":"USD","timestamp":1569801600}],"quarterlyOtherNonCurrentLiabilities":[{"value":265000,"currencyCode":"USD","timestamp":1419984000},{"value":249000,"currencyCode":"USD","timestamp":1451520000},{"value":31742000,"currencyCode":"USD","timestamp":1475193600},{"value":62406000,"currencyCode":"USD","timestamp":1483142400},{"value":11104000,"currencyCode":"USD","timestamp":1506729600}],"trailingTaxProvision":[{"value":1655000,"currencyCode":"USD","timestamp":1569801600}]}