[{"timestamp":1293753600000,"symbol":"PQG","sector":"basic_materials","ProfitMargin":1.0601275131,"ROE":null,"ROA":null,"CurrentRatio":null,"PayoutRatio":null},{"timestamp":1325289600000,"symbol":"PQG","sector":"basic_materials","ProfitMargin":-5.861614666,"ROE":-58.5498262085,"ROA":-2.8036000081,"CurrentRatio":2.2875273387,"PayoutRatio":null},{"timestamp":1356912000000,"symbol":"PQG","sector":"basic_materials","ProfitMargin":0.4778840357,"ROE":4.6426652337,"ROA":0.2221574644,"CurrentRatio":2.445190957,"PayoutRatio":null},{"timestamp":1451520000000,"symbol":"PQG","sector":"basic_materials","ProfitMargin":2.9384763742,"ROE":4.8564980684,"ROA":1.134040467,"CurrentRatio":1.2712165645,"PayoutRatio":null},{"timestamp":1483142400000,"symbol":"PQG","sector":"basic_materials","ProfitMargin":-7.4936782133,"ROE":-7.7962224308,"ROA":-1.8721164146,"CurrentRatio":2.0325670814,"PayoutRatio":null},{"timestamp":1514678400000,"symbol":"PQG","sector":"basic_materials","ProfitMargin":3.9127776646,"ROE":3.5380835381,"ROA":1.3044955271,"CurrentRatio":1.9036061026,"PayoutRatio":null},{"timestamp":1546214400000,"symbol":"PQG","sector":"basic_materials","ProfitMargin":3.6251709986,"ROE":3.5128946734,"ROA":1.3472292832,"CurrentRatio":2.1854460094,"PayoutRatio":null}]